eduval/__init__.py
eduval/main.py
eduval/tests/__init__.py
eduval/tests/test_modules.py
eduval-1.0.2.dist-info/METADATA
eduval-1.0.2.dist-info/WHEEL
eduval-1.0.2.dist-info/top_level.txt
eduval-1.0.2.dist-info/RECORD
